{
    "version": "7.5.257",
    "homepage": "https://toggl.com/",
    "description": "A leading time tracking tool",
    "license": "BSD-3-Clause",
    "architecture": {
        "32bit": {
            "url": "https://github.com/toggl-open-source/toggldesktop/releases/download/v7.5.257/TogglDesktopInstaller-7.5.257.exe#/dl.7z",
            "hash": "4a7ba05635cf2b86de3f286ebf3b4dc55b0ef43453818750833575ca985bf3bb"
        },
        "64bit": {
            "url": "https://github.com/toggl-open-source/toggldesktop/releases/download/v7.5.257/TogglDesktopInstaller-x64-7.5.257.exe#/dl.7z",
            "hash": "a46757b399f05103ff722e133287e760d80b4aa40403d88660dc611982190b76"
        }
    },
    "pre_install": "Remove-Item \"$dir\\`$*\", \"$dir\\Uninstall.exe\" -Recurse",
    "bin": "TogglDesktop.exe",
    "shortcuts": [
        [
            "TogglDesktop.exe",
            "Toggl Desktop"
        ]
    ],
    "checkver": {
        "github": "https://github.com/toggl-open-source/toggldesktop",
        "regex": "tag/v([\\w.-]+)"
    },
    "autoupdate": {
        "architecture": {
            "64bit": {
                "url": "https://github.com/toggl-open-source/toggldesktop/releases/download/v$version/TogglDesktopInstaller-x64-$version.exe#/dl.7z"
            },
            "32bit": {
                "url": "https://github.com/toggl-open-source/toggldesktop/releases/download/v$version/TogglDesktopInstaller-$version.exe#/dl.7z"
            }
        }
    }
}
