{
    "version": "7.5.255",
    "homepage": "https://toggl.com/",
    "description": "A leading time tracking tool",
    "license": "BSD-3-Clause",
    "architecture": {
        "32bit": {
            "url": "https://github.com/toggl-open-source/toggldesktop/releases/download/v7.5.255/TogglDesktopInstaller-7.5.255.exe#/dl.7z",
            "hash": "12e419209929a275aa5b30d0691a24afb3d8feef145c4b156822a40a320593ca"
        },
        "64bit": {
            "url": "https://github.com/toggl-open-source/toggldesktop/releases/download/v7.5.255/TogglDesktopInstaller-x64-7.5.255.exe#/dl.7z",
            "hash": "97e79585366d21f9b5c63cd16001965bd9e49dc903e5ba73a892b11aed3a784e"
        }
    },
    "pre_install": "Remove-Item \"$dir\\`$*\", \"$dir\\Uninstall.exe\" -Recurse",
    "bin": "TogglDesktop.exe",
    "shortcuts": [
        [
            "TogglDesktop.exe",
            "Toggl Desktop"
        ]
    ],
    "checkver": {
        "github": "https://github.com/toggl-open-source/toggldesktop",
        "regex": "tag/v([\\w.-]+)"
    },
    "autoupdate": {
        "architecture": {
            "64bit": {
                "url": "https://github.com/toggl-open-source/toggldesktop/releases/download/v$version/TogglDesktopInstaller-x64-$version.exe#/dl.7z"
            },
            "32bit": {
                "url": "https://github.com/toggl-open-source/toggldesktop/releases/download/v$version/TogglDesktopInstaller-$version.exe#/dl.7z"
            }
        }
    }
}
